{
"label": "a",
"gestures": [
{
"l_hand_position": null,
"l_wrist": null,
"l_thumb_cmc": null,
"l_thumb_mcp": null,
"l_thumb_ip": null,
"l_thumb_tip": null,
"l_index_mcp": null,
"l_index_pip": null,
"l_index_dip": null,
"l_index_tip": null,
"l_middle_mcp": null,
"l_middle_pip": null,
"l_middle_dip": null,
"l_middle_tip": null,
"l_ring_mcp": null,
"l_ring_pip": null,
"l_ring_dip": null,
"l_ring_tip": null,
"l_pinky_mcp": null,
"l_pinky_pip": null,
"l_pinky_dip": null,
"l_pinky_tip": null,
"r_hand_position": [
-0.30694587528705597,
0.11509591341018677,
-0.47608441300690174
],
"r_wrist": [
-0.3570197360461517,
0.9166604399246256,
-0.17964004550970167
],
"r_thumb_cmc": [
0.09794905194180788,
0.7498925825374544,
-0.21333094668630168
],
"r_thumb_mcp": [
0.4028171200582117,
0.3191636679164959,
-0.17334835373118096
],
"r_thumb_ip": [
0.5403666433435903,
-0.15441096840313442,
-0.15982953137963993
],
"r_thumb_tip": [
0.5312451550205369,
-0.47531668903835816,
-0.14065787478463
],
"r_index_mcp": [
0.23587073696515687,
0.051788348530815126,
0.027003621984799744
],
"r_index_pip": [
0.3497706969605435,
-0.3166000611656773,
-0.0916262898435051
],
"r_index_dip": [
0.2458523945983763,
-0.16170377147056111,
-0.1798575564622848
],
"r_index_tip": [
0.15907043336252275,
0.07169860976302904,
-0.21116337039243743
],
"r_middle_mcp": [
0.0,
0.0,
0.0
],
"r_middle_pip": [
0.11398580903388987,
-0.35813308726647974,
-0.16436466843511705
],
"r_middle_dip": [
0.01473267997656556,
-0.04111172782058588,
-0.2564462442995141
],
"r_middle_tip": [
-0.04529851939066634,
0.26894992730440753,
-0.26006071827360155
],
"r_ring_mcp": [
-0.23802849154698896,
-0.01121880160007232,
-0.05741113875879255
],
"r_ring_pip": [
-0.1479134162073706,
-0.29134141602754654,
-0.2638285480676098
],
"r_ring_dip": [
-0.21983722579500004,
0.11466297550448247,
-0.2872652586282555
],
"r_ring_tip": [
-0.24702831376202022,
0.42959619979742175,
-0.22850230881373904
],
"r_pinky_mcp": [
-0.4858519442523298,
0.0182465583530588,
-0.11407270740060166
],
"r_pinky_pip": [
-0.39652708300897327,
-0.16319958183634617,
-0.26280153557228236
],
"r_pinky_dip": [
-0.4221140139749136,
0.15132622329081508,
-0.2606155050929902
],
"r_pinky_tip": [
-0.41585878664011394,
0.40481839881758286,
-0.21048320634092904
],
"l_hand_velocity": null,
"r_hand_velocity": null,
"m_nose_point": null,
"m_top_nose": null,
"m_eyebrows": null,
"m_forehead": null,
"m_top_chin": null,
"m_bot_up_lip": null,
"m_top_low_lip": null,
"m_bot_nose": null,
"m_chin": null,
"m_nose": null,
"l_eye_exterior": null,
"l_temple": null,
"l_mid_chin": null,
"l_up_lip": null,
"l_ext_nostril": null,
"l_mid_cheek": null,
"l_mid_eyebrow": null,
"l_ext_eyebrow": null,
"l_ext_lips": null,
"l_jaw_angle": null,
"l_mid_ext_face": null,
"l_int_eyebrow": null,
"l_mid_jaw": null,
"l_mid_bot_eyelid": null,
"l_ext_mouth": null,
"l_top_eyelid": null,
"l_eye_int": null,
"l_pupil": null,
"r_eye_exterior": null,
"r_temple": null,
"r_mid_chin": null,
"r_up_lip": null,
"r_ext_nostril": null,
"r_mid_cheek": null,
"r_mid_eyebrow": null,
"r_ext_eyebrow": null,
"r_ext_lips": null,
"r_jaw_angle": null,
"r_mid_ext_face": null,
"r_int_eyebrow": null,
"r_mid_jaw": null,
"r_mid_bot_eyelid": null,
"r_ext_mouth": null,
"r_top_eyelid": null,
"r_eye_int": null,
"r_pupil": null,
"l_shoulder": null,
"l_elbow": null,
"l_hip": null,
"l_knee": null,
"l_ankle": null,
"l_body_wrist": null,
"r_shoulder": null,
"r_elbow": null,
"r_hip": null,
"r_knee": null,
"r_ankle": null,
"r_body_wrist": null,
"m_face_position": null,
"m_body_position": null,
"m_face_scale": null,
"m_body_scale": null,
"l_hand_scale": null,
"r_hand_scale": [
0.13313125965006015,
0.13313125965006015,
0.13313125965006015
]
}
],
"framerate": 30,
"mirrorable": true,
"invalid": false
}