{
"label": "m",
"gestures": [
{
"l_hand_position": null,
"l_wrist": null,
"l_thumb_cmc": null,
"l_thumb_mcp": null,
"l_thumb_ip": null,
"l_thumb_tip": null,
"l_index_mcp": null,
"l_index_pip": null,
"l_index_dip": null,
"l_index_tip": null,
"l_middle_mcp": null,
"l_middle_pip": null,
"l_middle_dip": null,
"l_middle_tip": null,
"l_ring_mcp": null,
"l_ring_pip": null,
"l_ring_dip": null,
"l_ring_tip": null,
"l_pinky_mcp": null,
"l_pinky_pip": null,
"l_pinky_dip": null,
"l_pinky_tip": null,
"r_hand_position": [
0.052044689655303955,
-0.02591991424560547,
-0.5273184552788734
],
"r_wrist": [
-0.7401532573164057,
0.6523220556358875,
0.16324549431725396
],
"r_thumb_cmc": [
-0.5492641480125888,
0.06320952912597794,
0.27114754030085947
],
"r_thumb_mcp": [
-0.2571222526227367,
-0.25332038457049716,
0.28394917070959225
],
"r_thumb_ip": [
0.03234009870144208,
-0.333600208644164,
0.2848177941782097
],
"r_thumb_tip": [
0.23357802534251018,
-0.26625881045878896,
0.29756019848875426
],
"r_index_mcp": [
-0.08398018075295455,
-0.32790061218810845,
0.060218972913043435
],
"r_index_pip": [
0.44775277506071826,
-0.45290474437321765,
0.06066706993632155
],
"r_index_dip": [
0.5069777156631433,
-0.2815241619593425,
0.15180552216518134
],
"r_index_tip": [
0.4164032136511328,
-0.1683398715686467,
0.2372903196256894
],
"r_middle_mcp": [
0.0,
0.0,
0.0
],
"r_middle_pip": [
0.5088017147539732,
-0.07883907493826227,
0.017444918662539943
],
"r_middle_dip": [
0.4366502803018314,
0.043502966013716116,
0.11140723474453958
],
"r_middle_tip": [
0.27704697614178103,
0.0791008674264013,
0.1802089733707268
],
"r_ring_mcp": [
0.03586414615402386,
0.3681315282803426,
-0.03687812455897666
],
"r_ring_pip": [
0.46905912179267595,
0.2861562861882515,
0.006540571432303206
],
"r_ring_dip": [
0.3515413643177032,
0.3585531288367577,
0.11155503285481824
],
"r_ring_tip": [
0.18988432480172135,
0.38020176479470397,
0.17077197261911062
],
"r_pinky_mcp": [
0.022728218313795838,
0.7146956297011005,
-0.06125196243915871
],
"r_pinky_pip": [
0.34840947132694605,
0.6172051756588919,
-0.013327107592620714
],
"r_pinky_dip": [
0.2522650224720536,
0.6301095863327384,
0.07847337799107655
],
"r_pinky_tip": [
0.10876747712652149,
0.6402571618253657,
0.1437645539265604
],
"l_hand_velocity": null,
"r_hand_velocity": null,
"m_nose_point": null,
"m_top_nose": null,
"m_eyebrows": null,
"m_forehead": null,
"m_top_chin": null,
"m_bot_up_lip": null,
"m_top_low_lip": null,
"m_bot_nose": null,
"m_chin": null,
"m_nose": null,
"l_eye_exterior": null,
"l_temple": null,
"l_mid_chin": null,
"l_up_lip": null,
"l_ext_nostril": null,
"l_mid_cheek": null,
"l_mid_eyebrow": null,
"l_ext_eyebrow": null,
"l_ext_lips": null,
"l_jaw_angle": null,
"l_mid_ext_face": null,
"l_int_eyebrow": null,
"l_mid_jaw": null,
"l_mid_bot_eyelid": null,
"l_ext_mouth": null,
"l_top_eyelid": null,
"l_eye_int": null,
"l_pupil": null,
"r_eye_exterior": null,
"r_temple": null,
"r_mid_chin": null,
"r_up_lip": null,
"r_ext_nostril": null,
"r_mid_cheek": null,
"r_mid_eyebrow": null,
"r_ext_eyebrow": null,
"r_ext_lips": null,
"r_jaw_angle": null,
"r_mid_ext_face": null,
"r_int_eyebrow": null,
"r_mid_jaw": null,
"r_mid_bot_eyelid": null,
"r_ext_mouth": null,
"r_top_eyelid": null,
"r_eye_int": null,
"r_pupil": null,
"l_shoulder": null,
"l_elbow": null,
"l_hip": null,
"l_knee": null,
"l_ankle": null,
"l_body_wrist": null,
"r_shoulder": null,
"r_elbow": null,
"r_hip": null,
"r_knee": null,
"r_ankle": null,
"r_body_wrist": null,
"m_face_position": null,
"m_body_position": null,
"m_face_scale": null,
"m_body_scale": null,
"l_hand_scale": null,
"r_hand_scale": [
0.1673440449775071,
0.1673440449775071,
0.1673440449775071
]
}
],
"framerate": 30,
"mirrorable": true,
"invalid": false
}