{
"label": "c",
"gestures": [
{
"l_hand_position": null,
"l_wrist": null,
"l_thumb_cmc": null,
"l_thumb_mcp": null,
"l_thumb_ip": null,
"l_thumb_tip": null,
"l_index_mcp": null,
"l_index_pip": null,
"l_index_dip": null,
"l_index_tip": null,
"l_middle_mcp": null,
"l_middle_pip": null,
"l_middle_dip": null,
"l_middle_tip": null,
"l_ring_mcp": null,
"l_ring_pip": null,
"l_ring_dip": null,
"l_ring_tip": null,
"l_pinky_mcp": null,
"l_pinky_pip": null,
"l_pinky_dip": null,
"l_pinky_tip": null,
"r_hand_position": [
0.10417729616165161,
0.14096200466156006,
-0.5289140082895756
],
"r_wrist": [
-0.316030367119863,
0.9424830732973529,
0.10885983467772346
],
"r_thumb_cmc": [
-0.022928938071432023,
0.8131862848130413,
0.01057936480077737
],
"r_thumb_mcp": [
0.2150299859247268,
0.5306272573637401,
-0.07430665232701196
],
"r_thumb_ip": [
0.40641429408650137,
0.32874273516138486,
-0.16969562540618524
],
"r_thumb_tip": [
0.622555742657471,
0.1301483937220446,
-0.27023477653135947
],
"r_index_mcp": [
0.09354126180060507,
-0.0048360855015505445,
0.05950972380645717
],
"r_index_pip": [
0.2542303062854925,
-0.4319815253806019,
-0.036630834372885
],
"r_index_dip": [
0.38894034197661137,
-0.6647029088632723,
-0.1252137957832438
],
"r_index_tip": [
0.5010059812145974,
-0.8725220761037583,
-0.20607936522903103
],
"r_middle_mcp": [
0.0,
0.0,
0.0
],
"r_middle_pip": [
0.19099025841277345,
-0.34339775051332966,
-0.17167344771555793
],
"r_middle_dip": [
0.37486832277950993,
-0.25542412443166895,
-0.3084390048764092
],
"r_middle_tip": [
0.49740275979107196,
-0.12256024323088727,
-0.38808058814462404
],
"r_ring_mcp": [
-0.12904927318069642,
0.04213280448374201,
-0.07855240653637838
],
"r_ring_pip": [
-0.0018726339153839402,
-0.42063778457094664,
-0.21499785437664304
],
"r_ring_dip": [
0.11769565868712537,
-0.6630856443182547,
-0.3134419892964219
],
"r_ring_tip": [
0.213180465405782,
-0.8253015193795679,
-0.37556182284851825
],
"r_pinky_mcp": [
-0.2930659735470972,
0.136786875342033,
-0.1683067739524344
],
"r_pinky_pip": [
-0.19886160411078693,
-0.22350788997783708,
-0.2733029957579389
],
"r_pinky_dip": [
-0.0914264982273782,
-0.45252529558065996,
-0.34090625821331183
],
"r_pinky_tip": [
-0.0036525898431041814,
-0.6482205887811932,
-0.395235811256362
],
"l_hand_velocity": null,
"r_hand_velocity": null,
"m_nose_point": null,
"m_top_nose": null,
"m_eyebrows": null,
"m_forehead": null,
"m_top_chin": null,
"m_bot_up_lip": null,
"m_top_low_lip": null,
"m_bot_nose": null,
"m_chin": null,
"m_nose": null,
"l_eye_exterior": null,
"l_temple": null,
"l_mid_chin": null,
"l_up_lip": null,
"l_ext_nostril": null,
"l_mid_cheek": null,
"l_mid_eyebrow": null,
"l_ext_eyebrow": null,
"l_ext_lips": null,
"l_jaw_angle": null,
"l_mid_ext_face": null,
"l_int_eyebrow": null,
"l_mid_jaw": null,
"l_mid_bot_eyelid": null,
"l_ext_mouth": null,
"l_top_eyelid": null,
"l_eye_int": null,
"l_pupil": null,
"r_eye_exterior": null,
"r_temple": null,
"r_mid_chin": null,
"r_up_lip": null,
"r_ext_nostril": null,
"r_mid_cheek": null,
"r_mid_eyebrow": null,
"r_ext_eyebrow": null,
"r_ext_lips": null,
"r_jaw_angle": null,
"r_mid_ext_face": null,
"r_int_eyebrow": null,
"r_mid_jaw": null,
"r_mid_bot_eyelid": null,
"r_ext_mouth": null,
"r_top_eyelid": null,
"r_eye_int": null,
"r_pupil": null,
"l_shoulder": null,
"l_elbow": null,
"l_hip": null,
"l_knee": null,
"l_ankle": null,
"l_body_wrist": null,
"r_shoulder": null,
"r_elbow": null,
"r_hip": null,
"r_knee": null,
"r_ankle": null,
"r_body_wrist": null,
"m_face_position": null,
"m_body_position": null,
"m_face_scale": null,
"m_body_scale": null,
"l_hand_scale": null,
"r_hand_scale": [
0.2656155891252532,
0.2656155891252532,
0.2656155891252532
]
}
],
"framerate": 30,
"mirrorable": true,
"invalid": false
}